kalshi_python_sync/__init__.py
kalshi_python_sync/api_client.py
kalshi_python_sync/api_response.py
kalshi_python_sync/auth.py
kalshi_python_sync/configuration.py
kalshi_python_sync/exceptions.py
kalshi_python_sync/py.typed
kalshi_python_sync/rest.py
kalshi_python_sync/api/__init__.py
kalshi_python_sync/api/api_keys_api.py
kalshi_python_sync/api/communications_api.py
kalshi_python_sync/api/events_api.py
kalshi_python_sync/api/exchange_api.py
kalshi_python_sync/api/fcm_api.py
kalshi_python_sync/api/incentive_programs_api.py
kalshi_python_sync/api/live_data_api.py
kalshi_python_sync/api/market_api.py
kalshi_python_sync/api/milestone_api.py
kalshi_python_sync/api/multivariate_api.py
kalshi_python_sync/api/order_groups_api.py
kalshi_python_sync/api/orders_api.py
kalshi_python_sync/api/portfolio_api.py
kalshi_python_sync/api/search_api.py
kalshi_python_sync/api/structured_targets_api.py
kalshi_python_sync/models/__init__.py
kalshi_python_sync/models/accept_quote_request.py
kalshi_python_sync/models/amend_order_request.py
kalshi_python_sync/models/amend_order_response.py
kalshi_python_sync/models/announcement.py
kalshi_python_sync/models/api_key.py
kalshi_python_sync/models/associated_event.py
kalshi_python_sync/models/batch_cancel_orders_individual_response.py
kalshi_python_sync/models/batch_cancel_orders_request.py
kalshi_python_sync/models/batch_cancel_orders_response.py
kalshi_python_sync/models/batch_create_orders_individual_response.py
kalshi_python_sync/models/batch_create_orders_request.py
kalshi_python_sync/models/batch_create_orders_response.py
kalshi_python_sync/models/batch_get_market_candlesticks_response.py
kalshi_python_sync/models/bid_ask_distribution.py
kalshi_python_sync/models/cancel_order_response.py
kalshi_python_sync/models/create_api_key_request.py
kalshi_python_sync/models/create_api_key_response.py
kalshi_python_sync/models/create_market_in_multivariate_event_collection_request.py
kalshi_python_sync-3.4.0.dist-info/METADATA
kalshi_python_sync-3.4.0.dist-info/WHEEL
kalshi_python_sync-3.4.0.dist-info/top_level.txt
kalshi_python_sync-3.4.0.dist-info/RECORD
