Metadata-Version: 2.4
Name: kalshi_python_sync
Version: 3.4.0
Summary: Manually defined OpenAPI spec for endpoints being migrated to spec-first approach
Home-page: https://github.com/Kalshi/exchange-infra
Author: OpenAPI Generator community
Author-email: Kalshi <support@kalshi.com>
License: LicenseRef-Proprietary
Project-URL: Repository, https://github.com/Kalshi/exchange-infra
Keywords: OpenAPI,OpenAPI-Generator,Kalshi Trading API
Requires-Python: >=3.13
Requires-Dist: urllib3<3.0.0,>=2.1.0
Requires-Dist: python-dateutil>=2.8.2
Requires-Dist: pydantic>=2
Requires-Dist: typing-extensions>=4.7.1
Requires-Dist: lazy-imports<2,>=1
Requires-Dist: cryptography>=41.0.0
Provides-Extra: dev
Requires-Dist: pytest>=7.2.1; extra == "dev"
Requires-Dist: pytest-cov>=2.8.1; extra == "dev"
Requires-Dist: mypy>=1.5; extra == "dev"
Dynamic: author
Dynamic: home-page
